mindtouch2zim/__about__.py
mindtouch2zim/__init__.py
mindtouch2zim/__main__.py
mindtouch2zim/asset.py
mindtouch2zim/client.py
mindtouch2zim/constants.py
mindtouch2zim/context.py
mindtouch2zim/download.py
mindtouch2zim/entrypoint.py
mindtouch2zim/errors.py
mindtouch2zim/html_rewriting.py
mindtouch2zim/html_utils.py
mindtouch2zim/processor.py
mindtouch2zim/ui.py
mindtouch2zim/utils.py
mindtouch2zim/vimeo.py
mindtouch2zim/zimconfig.py
mindtouch2zim/libretexts/detailed_licensing.py
mindtouch2zim/libretexts/errors.py
mindtouch2zim/libretexts/glossary.py
mindtouch2zim/libretexts/index.py
mindtouch2zim/libretexts/table_of_content.py
mindtouch2zim/mathjax/LICENSE
mindtouch2zim/mathjax/README.md
mindtouch2zim/mathjax/es5/core.js
mindtouch2zim/mathjax/es5/latest.js
mindtouch2zim/mathjax/es5/loader.js
mindtouch2zim/mathjax/es5/mml-chtml.js
mindtouch2zim/mathjax/es5/mml-svg.js
mindtouch2zim/mathjax/es5/node-main.js
mindtouch2zim/mathjax/es5/startup.js
mindtouch2zim/mathjax/es5/tex-chtml-full-speech.js
mindtouch2zim/mathjax/es5/tex-chtml-full.js
mindtouch2zim/mathjax/es5/tex-chtml.js
mindtouch2zim/mathjax/es5/tex-mml-chtml.js
mindtouch2zim/mathjax/es5/tex-mml-svg.js
mindtouch2zim/mathjax/es5/tex-svg-full.js
mindtouch2zim/mathjax/es5/tex-svg.js
mindtouch2zim/mathjax/es5/a11y/assistive-mml.js
mindtouch2zim/mathjax/es5/a11y/complexity.js
mindtouch2zim/mathjax/es5/a11y/explorer.js
mindtouch2zim/mathjax/es5/a11y/semantic-enrich.js
mindtouch2zim/mathjax/es5/a11y/sre.js
mindtouch2zim/mathjax/es5/adaptors/liteDOM.js
mindtouch2zim/mathjax/es5/input/asciimath.js
mindtouch2zim/mathjax/es5/input/mml.js
mindtouch2zim/mathjax/es5/input/tex-base.js
mindtouch2zim/mathjax/es5/input/tex-full.js
mindtouch2zim/mathjax/es5/input/tex.js
mindtouch2zim/mathjax/es5/input/mml/entities.js
mindtouch2zim/mathjax/es5/input/mml/extensions/mml3.js
mindtouch2zim/mathjax/es5/input/mml/extensions/mml3.sef.json
mindtouch2zim/mathjax/es5/input/tex/extensions/action.js
mindtouch2zim-0.1.1.dist-info/METADATA
mindtouch2zim-0.1.1.dist-info/WHEEL
mindtouch2zim-0.1.1.dist-info/entry_points.txt
mindtouch2zim-0.1.1.dist-info/RECORD
