Metadata-Version: 2.1
Name: mindtouch2zim
Version: 0.1.1
Summary: Make ZIM file from Mindtouch / Nice CXone Expert libraries
Project-URL: Donate, https://www.kiwix.org/en/support-us/
Project-URL: Homepage, https://www.kiwix.org
Author-email: openZIM <dev@openzim.org>
License: GPL-3.0-or-later
Keywords: cxone,expert,mindouch,nice,offline,openzim,zim
Classifier: License :: OSI Approved :: GNU General Public License v3 or later (GPLv3+)
Classifier: Programming Language :: Python :: 3
Classifier: Programming Language :: Python :: 3.12
Requires-Python: <3.13,>=3.12
Requires-Dist: backoff==2.2.1
Requires-Dist: beautifulsoup4==4.12.3
Requires-Dist: jinja2==3.1.5
Requires-Dist: joblib==1.4.2
Requires-Dist: kiwixstorage==0.9.0
Requires-Dist: lxml==5.3.0
Requires-Dist: pif==0.8.2
Requires-Dist: pydantic==2.10.5
Requires-Dist: requests==2.32.3
Requires-Dist: schedule==1.2.2
Requires-Dist: tinycss2==1.4.0
Requires-Dist: types-beautifulsoup4==4.12.0.20241020
Requires-Dist: types-requests==2.32.0.20241016
Requires-Dist: zimscraperlib==5.0.0
Provides-Extra: check
Requires-Dist: pyright==1.1.391; extra == 'check'
Provides-Extra: dev
Requires-Dist: debugpy==1.8.11; extra == 'dev'
Requires-Dist: humanfriendly==10.0; extra == 'dev'
Requires-Dist: mindtouch2zim[check]; extra == 'dev'
Requires-Dist: mindtouch2zim[lint]; extra == 'dev'
Requires-Dist: mindtouch2zim[scripts]; extra == 'dev'
Requires-Dist: mindtouch2zim[test]; extra == 'dev'
Requires-Dist: pre-commit==4.0.1; extra == 'dev'
Provides-Extra: lint
Requires-Dist: black==24.10.0; extra == 'lint'
Requires-Dist: ruff==0.9.1; extra == 'lint'
Provides-Extra: scripts
Requires-Dist: invoke==2.2.0; extra == 'scripts'
Provides-Extra: test
Requires-Dist: coverage==7.6.10; extra == 'test'
Requires-Dist: pytest==8.3.4; extra == 'test'
